confsave/__init__.py
confsave/app.py
confsave/cmd.py
confsave/commands.py
confsave/filematching.py
confsave/models.py
confsave/repo.py
confsave/tests/__init__.py
confsave/tests/test_app.py
confsave/tests/test_cmd.py
confsave/tests/test_commands.py
confsave/tests/test_models.py
confsave/tests/test_repo.py
confsave-0.3.dist-info/DESCRIPTION.rst
confsave-0.3.dist-info/METADATA
confsave-0.3.dist-info/RECORD
confsave-0.3.dist-info/WHEEL
confsave-0.3.dist-info/entry_points.txt
confsave-0.3.dist-info/metadata.json
confsave-0.3.dist-info/top_level.txt
