Metadata-Version: 2.0
Name: confsave
Version: 0.3
Summary: Configuration Saver
Home-page: https://github.com/socek/confsave
Author: UNKNOWN
Author-email: UNKNOWN
License: Apache License 2.0
Platform: UNKNOWN
Requires-Dist: GitPython (==2.1.3)
Requires-Dist: freezegun (==0.3.9)
Requires-Dist: mock (==2.0.0)
Requires-Dist: pytest (==3.0.7)
Requires-Dist: pyyaml (==3.12)
